alibabacloud_tea_sse/__init__.py
alibabacloud_tea_sse/core.py
alibabacloud_tea_sse/event.py
alibabacloud_tea_sse/exceptions.py
alibabacloud_tea_sse/iterator.py
alibabacloud_tea_sse/model.py
alibabacloud_tea_sse/request.py
alibabacloud_tea_sse/response.py
alibabacloud_tea_sse/stream.py
alibabacloud_tea_sse-1.0.4.dist-info/METADATA
alibabacloud_tea_sse-1.0.4.dist-info/WHEEL
alibabacloud_tea_sse-1.0.4.dist-info/top_level.txt
alibabacloud_tea_sse-1.0.4.dist-info/RECORD
