Metadata-Version: 2.1
Name: alibabacloud-tea-sse
Version: 1.0.4
Summary: The tea module of alibabaCloud Python SDK.
Home-page: https://github.com/aliyun/tea-python
Author: Alibaba Cloud
Author-email: alibaba-cloud-sdk-dev-team@list.alibaba-inc.com
License: Apache License 2.0
Keywords: alibabacloud,sdk,tea
Platform: any
Classifier: Development Status :: 5 - Production/Stable
Classifier: Intended Audience :: Developers
Classifier: License :: OSI Approved :: Apache Software License
Classifier: Programming Language :: Python :: 3
Classifier: Programming Language :: Python :: 3.6
Classifier: Programming Language :: Python :: 3.7
Classifier: Programming Language :: Python :: 3.8
Classifier: Programming Language :: Python :: 3.9
Classifier: Programming Language :: Python :: 3.10
Classifier: Programming Language :: Python :: 3.11
Classifier: Programming Language :: Python :: 3.12
Classifier: Topic :: Software Development
Requires-Python: >=3.6
Requires-Dist: requests <3.0.0,>=2.21.0
Requires-Dist: aiohttp <4.0.0,>=3.7.0
